LICENSE
MANIFEST.in
README.rst
requirements.txt
setup.py
django_spillway.egg-info/PKG-INFO
django_spillway.egg-info/SOURCES.txt
django_spillway.egg-info/dependency_links.txt
django_spillway.egg-info/requires.txt
django_spillway.egg-info/top_level.txt
spillway/__init__.py
spillway/carto.py
spillway/collections.py
spillway/colors.py
spillway/compat.py
spillway/fields.py
spillway/filters.py
spillway/generics.py
spillway/mixins.py
spillway/models.py
spillway/pagination.py
spillway/query.py
spillway/serializers.py
spillway/urls.py
spillway/validators.py
spillway/views.py
spillway/viewsets.py
spillway/forms/__init__.py
spillway/forms/fields.py
spillway/forms/forms.py
spillway/renderers/__init__.py
spillway/renderers/gdal.py
spillway/renderers/renderers.py
spillway/templates/spillway/features.svg
spillway/templates/spillway/placemarks.kml