Metadata-Version: 2.1
Name: django-spillway
Version: 0.8.1
Summary: Geodata extensions for Django REST Framework
Home-page: https://github.com/bkg/django-spillway
Author: Brian Galey
Author-email: bkgaley@gmail.com
License: BSD
Platform: UNKNOWN
Classifier: Development Status :: 4 - Beta
Classifier: Intended Audience :: Developers
Classifier: License :: OSI Approved :: BSD License
Classifier: Natural Language :: English
Classifier: Programming Language :: Python :: 2
Classifier: Programming Language :: Python :: 2.7
Classifier: Programming Language :: Python :: 3
Classifier: Programming Language :: Python :: 3.5
Classifier: Programming Language :: Python :: 3.6
Provides-Extra: mapnik
